<?xml version="1.0" encoding="UTF-8"?>
<metadata xml:lang="en"><Esri><CreaDate>20180918</CreaDate><CreaTime>10322800</CreaTime><ArcGISFormat>1.0</ArcGISFormat><SyncOnce>TRUE</SyncOnce><DataProperties><itemProps><itemLocation><linkage Sync="TRUE">file://\\H0W1BZ1\C$\Users\fm25\Desktop\HC_info\hc_subwshds</linkage><protocol Sync="TRUE">Local Area Network</protocol></itemLocation></itemProps><copyHistory><copy source="P:\GISData\TX\Harris_cty\hc_subwshds" dest="\\H0W1BZ1\C$\Users\fm25\Desktop\HC_info\hc_subwshds" date="20180918" time="10322800"></copy></copyHistory></DataProperties></Esri></metadata>
